pyodbch/__init__.py
pyodbch/run_sp.py
pyodbc_helpers-1.0.0.dist-info/LICENSE
pyodbc_helpers-1.0.0.dist-info/METADATA
pyodbc_helpers-1.0.0.dist-info/WHEEL
pyodbc_helpers-1.0.0.dist-info/top_level.txt
pyodbc_helpers-1.0.0.dist-info/RECORD
