Metadata-Version: 2.1
Name: pyodbc-helpers
Version: 1.0.0
Summary: Additional features related to pyodbc.
Home-page: https://github.com/srianbury/pyodbc-helpers
Author: srianbury
License: MIT
Platform: UNKNOWN
Classifier: Programming Language :: Python
Classifier: Programming Language :: Python :: 3
Requires-Dist: pyodbc
